db_inspector/__init__.py
db_inspector/main.py
db_inspector/checks/__init__.py
db_inspector/checks/backup_check.py
db_inspector/checks/base.py
db_inspector/checks/connection_check.py
db_inspector/checks/performance_check.py
db_inspector/checks/replication_check.py
db_inspector/config/__init__.py
db_inspector/config/config_loader.py
db_inspector/connectors/__init__.py
db_inspector/connectors/mongodb_connector.py
db_inspector/connectors/mysql_connector.py
db_inspector/connectors/pg_connector.py
db_inspector/connectors/redis_connector.py
db_inspector/pipelines/__init__.py
db_inspector/pipelines/base.py
db_inspector/pipelines/base_pipeline.py
db_inspector/pipelines/pg_pipeline.py
db_inspector/reports/__init__.py
db_inspector/reports/doc_report.py
db_inspector/reports/html_report.py
db_inspector/reports/json_report.py
db_inspector/reports/pdf_report.py
db_inspector/utils/__init__.py
db_inspector/utils/connection.py
db_inspector/utils/data_sanitizer.py
db_inspector/utils/report_generator.py
dbinspector_tool-0.0.1.dist-info/METADATA
dbinspector_tool-0.0.1.dist-info/WHEEL
dbinspector_tool-0.0.1.dist-info/entry_points.txt
dbinspector_tool-0.0.1.dist-info/top_level.txt
dbinspector_tool-0.0.1.dist-info/RECORD
