Metadata-Version: 2.2
Name: dbinspector-tool
Version: 0.0.1
Summary: A database inspector tool
Home-page: https://github.com/ethanxv24/DBInspector
Author: Ethan Xv
Author-email: kasetacor@gmail.com
License: BSD License
Classifier: Development Status :: 3 - Alpha
Classifier: Intended Audience :: Developers
Classifier: License :: OSI Approved :: BSD License
Classifier: Programming Language :: Python :: 3
Classifier: Programming Language :: Python :: 3.7
Classifier: Programming Language :: Python :: 3.8
Classifier: Programming Language :: Python :: 3.9
Requires-Python: >=3.7
Requires-Dist: click
Requires-Dist: psycopg2
Requires-Dist: mysql-connector-python
Requires-Dist: toml
Dynamic: author
Dynamic: author-email
Dynamic: classifier
Dynamic: description
Dynamic: description-content-type
Dynamic: home-page
Dynamic: license
Dynamic: requires-dist
Dynamic: requires-python
Dynamic: summary
